Automail.py
Automail-0.1.4.data/data/LICENSE.txt
Automail-0.1.4.dist-info/LICENSE.txt
Automail-0.1.4.dist-info/METADATA
Automail-0.1.4.dist-info/WHEEL
Automail-0.1.4.dist-info/top_level.txt
Automail-0.1.4.dist-info/RECORD
