Metadata-Version: 2.1
Name: Automail
Version: 0.1.4
Summary: sends bulk automated emails
Home-page: https://github.com/Preetam2114/Automail
Author: Preetam Rane
Author-email: preetamrane2114@gmail.com
License: UNKNOWN
Keywords: Email
Platform: UNKNOWN
Classifier: Environment :: Console
Classifier: Development Status :: 5 - Production/Stable
Classifier: Intended Audience :: Developers
Classifier: Topic :: Communications :: Email
Classifier: Programming Language :: Python :: 3
Classifier: Programming Language :: Python :: 3.6
Classifier: Programming Language :: Python :: 3.7
Classifier: Programming Language :: Python :: 3.8
Classifier: License :: OSI Approved :: MIT License
Classifier: Operating System :: OS Independent
Requires-Dist: yagmail
Requires-Dist: keyring
Requires-Dist: tqdm
